issuedb/__init__.py
issuedb/cli.py
issuedb/database.py
issuedb/date_utils.py
issuedb/git_cli.py
issuedb/git_repository.py
issuedb/git_utils.py
issuedb/models.py
issuedb/ollama_client.py
issuedb/py.typed
issuedb/repository.py
issuedb/similarity.py
issuedb/web.py
issuedb/data/__init__.py
issuedb/data/agents/PROMPT.txt
issuedb/data/agents/__init__.py
issuedb/static/favicon.svg
issuedb/static/fonts/JetBrainsMono-Bold.woff2
issuedb/static/fonts/JetBrainsMono-BoldItalic.woff2
issuedb/static/fonts/JetBrainsMono-ExtraBold.woff2
issuedb/static/fonts/JetBrainsMono-ExtraBoldItalic.woff2
issuedb/static/fonts/JetBrainsMono-ExtraLight.woff2
issuedb/static/fonts/JetBrainsMono-ExtraLightItalic.woff2
issuedb/static/fonts/JetBrainsMono-Italic.woff2
issuedb/static/fonts/JetBrainsMono-Light.woff2
issuedb/static/fonts/JetBrainsMono-LightItalic.woff2
issuedb/static/fonts/JetBrainsMono-Medium.woff2
issuedb/static/fonts/JetBrainsMono-MediumItalic.woff2
issuedb/static/fonts/JetBrainsMono-Regular.woff2
issuedb/static/fonts/JetBrainsMono-SemiBold.woff2
issuedb/static/fonts/JetBrainsMono-SemiBoldItalic.woff2
issuedb/static/fonts/JetBrainsMono-Thin.woff2
issuedb/static/fonts/JetBrainsMono-ThinItalic.woff2
issuedb-2.8.2.dist-info/licenses/LICENSE
issuedb-2.8.2.dist-info/METADATA
issuedb-2.8.2.dist-info/WHEEL
issuedb-2.8.2.dist-info/entry_points.txt
issuedb-2.8.2.dist-info/top_level.txt
issuedb-2.8.2.dist-info/RECORD
