Metadata-Version: 2.4
Name: issuedb
Version: 2.8.2
Summary: A command-line issue tracking system for software development projects
Author-email: Farshid Ashouri <farsheed.ashouri@gmail.com>
Maintainer-email: Farshid Ashouri <farsheed.ashouri@gmail.com>
License-Expression: Apache-2.0
Project-URL: Homepage, https://github.com/rodmena-limited/issue-queue
Project-URL: Repository, https://github.com/rodmena-limited/issue-queue
Project-URL: Bug Tracker, https://github.com/rodmena-limited/issue-queue/issues
Keywords: issue tracking,task management,cli,project management
Classifier: Development Status :: 5 - Production/Stable
Classifier: Intended Audience :: Developers
Classifier: Operating System :: OS Independent
Classifier: Programming Language :: Python :: 3
Classifier: Programming Language :: Python :: 3.8
Classifier: Programming Language :: Python :: 3.9
Classifier: Programming Language :: Python :: 3.10
Classifier: Programming Language :: Python :: 3.11
Classifier: Programming Language :: Python :: 3.12
Classifier: Programming Language :: Python :: 3.13
Classifier: Programming Language :: Python :: 3.14
Classifier: Topic :: Software Development :: Bug Tracking
Classifier: Topic :: Utilities
Classifier: Environment :: Console
Requires-Python: >=3.8
License-File: LICENSE
Provides-Extra: web
Requires-Dist: flask>=2.0; extra == "web"
Requires-Dist: waitress>=3.0.0; extra == "web"
Dynamic: license-file
